
{
  "@context": "http://schema.org",
  "name": "为正义而战 Sarrainodu",
  "url": "/subject/26830504/",
  "image": "https://img1.doubanio.com/view/photo/s_ratio_poster/public/p2364544788.jpg",
  "director": 
  [
  ]
,
  "author": 
  [
  ]
,
  "actor": 
  [
    {
      "@type": "Person",
      "url": "/celebrity/1217474/",
      "name": "阿卢·阿尔军 Allu Arjun"
    }
    ,
    {
      "@type": "Person",
      "url": "/celebrity/1073035/",
      "name": "婆罗门·安达姆 Brahmanandam"
    }
    ,
    {
      "@type": "Person",
      "url": "/celebrity/1427036/",
      "name": "阿迪 Aadhi"
    }
    ,
    {
      "@type": "Person",
      "url": "/celebrity/1430115/",
      "name": "乔伊·波德拉尼 Joy Badlani"
    }
  ]
,
  "datePublished": "2016-04-22",
  "genre": ["\u5267\u60c5", "\u52a8\u4f5c", "\u7231\u60c5"],
  "duration": "PT2H42M",
  "description": "Gana goes to a village named Parnasala on his father&#39;s orders to visit his friend&#39;s daughter for mar...",
  "@type": "Movie",
  "aggregateRating": {
    "@type": "AggregateRating",
    "ratingCount": "0",
    "bestRating": "10",
    "worstRating": "2",
    "ratingValue": ""
  }
}
