
{
  "@context": "http://schema.org",
  "name": "状态更新 Status Update",
  "url": "/subject/26837435/",
  "image": "https://img2.doubanio.com/view/photo/s_ratio_poster/public/p2513023373.jpg",
  "director": 
  [
    {
      "@type": "Person",
      "url": "/celebrity/1322160/",
      "name": "斯科特·斯皮尔 Scott Speer"
    }
  ]
,
  "author": 
  [
    {
      "@type": "Person",
      "url": "/celebrity/1446289/",
      "name": "杰森·费拉尔迪 Jason Filardi"
    }
  ]
,
  "actor": 
  [
    {
      "@type": "Person",
      "url": "/celebrity/1323997/",
      "name": "罗斯·林奇 Ross Lynch"
    }
    ,
    {
      "@type": "Person",
      "url": "/celebrity/1351403/",
      "name": "奥利维亚·霍尔特 Olivia Holt"
    }
    ,
    {
      "@type": "Person",
      "url": "/celebrity/1362735/",
      "name": "哈维·吉兰 Harvey Guillen"
    }
    ,
    {
      "@type": "Person",
      "url": "/celebrity/1341732/",
      "name": "考特尼·伊顿 Courtney Eaton"
    }
    ,
    {
      "@type": "Person",
      "url": "/celebrity/1322845/",
      "name": "格雷格·萨克因 Gregg Sulkin"
    }
    ,
    {
      "@type": "Person",
      "url": "/celebrity/1390320/",
      "name": "布瑞克·巴辛格 Brec Bassinger"
    }
    ,
    {
      "@type": "Person",
      "url": "/celebrity/1383501/",
      "name": "安德鲁·海尔 Andrew Herr"
    }
    ,
    {
      "@type": "Person",
      "url": "/celebrity/1390589/",
      "name": "奥斯汀·奥比晶瓦 Austin Obiajunwa"
    }
    ,
    {
      "@type": "Person",
      "url": "/celebrity/1102600/",
      "name": "Tyronne L&#39;Hirondelle Tyronne L&#39;Hirondelle"
    }
    ,
    {
      "@type": "Person",
      "url": "/celebrity/1010661/",
      "name": "尼古拉斯·李 Nicholas Lea"
    }
    ,
    {
      "@type": "Person",
      "url": "/celebrity/1393694/",
      "name": "梅根·塞雷纳·特雷纳 Megan Serena Trainer"
    }
    ,
    {
      "@type": "Person",
      "url": "/celebrity/1438330/",
      "name": "马基安·塔拉修克 Markian Tarasiuk"
    }
    ,
    {
      "@type": "Person",
      "url": "/celebrity/1032598/",
      "name": "吉莲·芭伯 Gillian Barber"
    }
    ,
    {
      "@type": "Person",
      "url": "/celebrity/1040523/",
      "name": "法米克·詹森 Famke Janssen"
    }
  ]
,
  "datePublished": "2018-03-30",
  "genre": ["\u559c\u5267"],
  "duration": "PT1H46M",
  "description": "Ross Lynch stars as Kyle Moore, a teenager who after being uprooted by his parents&#39; separation and u...",
  "@type": "Movie",
  "aggregateRating": {
    "@type": "AggregateRating",
    "ratingCount": "0",
    "bestRating": "10",
    "worstRating": "2",
    "ratingValue": ""
  }
}
