
{
  "@context": "http://schema.org",
  "name": "泰惊魂之古镜",
  "url": "/subject/26856017/",
  "image": "https://img1.doubanio.com/view/photo/s_ratio_poster/public/p2374301480.jpg",
  "director": 
  [
  ]
,
  "author": 
  [
  ]
,
  "actor": 
  [
  ]
,
  "datePublished": "",
  "genre": [],
  "duration": "PT1H6M",
  "description": "喜欢古董的叶帆带着妹妹小夕来泰国旅游，在恰图恰周末市场淘古董，偶遇一个极美的古镜，妹妹小夕一眼相中，疼爱妹妹的叶帆就把它买了下来送给小夕，小夕爱不释手，经常跑去一个人照镜子。咖啡馆里一个神秘的老人给他...",
  "@type": "Movie",
  "aggregateRating": {
    "@type": "AggregateRating",
    "ratingCount": "88",
    "bestRating": "10",
    "worstRating": "2",
    "ratingValue": "5.1"
  }
}
