
{
  "@context": "http://schema.org",
  "name": "嗜血审判",
  "url": "/subject/26895376/",
  "image": "https://img2.doubanio.com/view/photo/s_ratio_poster/public/p2406734562.jpg",
  "director": 
  [
  ]
,
  "author": 
  [
  ]
,
  "actor": 
  [
    {
      "@type": "Person",
      "url": "/celebrity/1370556/",
      "name": "刘夏 Xia Liu"
    }
  ]
,
  "datePublished": "2016-10-19",
  "genre": ["\u5267\u60c5", "\u60ac\u7591"],
  "duration": "PT1H15M",
  "description": "影片《杀人直播》讲述的是当红网络主播艾雪离（卓玲 饰）为了提高关注量，将杀害粉丝李杰（王若鑫 饰）的全过程公布至网络上，从而引发了广泛的社会舆论，她也因此被绳之以法的故事。身为李杰发小的林慕鱼（刘夏 ...",
  "@type": "Movie",
  "aggregateRating": {
    "@type": "AggregateRating",
    "ratingCount": "0",
    "bestRating": "10",
    "worstRating": "2",
    "ratingValue": ""
  }
}
