
{
  "@context": "http://schema.org",
  "name": "我的杀手女友",
  "url": "/subject/26894683/",
  "image": "https://img2.doubanio.com/view/photo/s_ratio_poster/public/p2416599143.jpg",
  "director": 
  [
    {
      "@type": "Person",
      "url": "/celebrity/1372733/",
      "name": "董汉新 "
    }
  ]
,
  "author": 
  [
  ]
,
  "actor": 
  [
  ]
,
  "datePublished": "2017-01-17",
  "genre": ["\u52a8\u4f5c", "\u7231\u60c5"],
  "duration": "PT1H8M",
  "description": "影片讲述了一个女杀手和一个小摄影师偶然相遇相杀的爱情故事。谢苗颠覆以往冷酷腹黑的高手形象，在此剧中成了一个一心想举办个人影展的普通小摄影师。
在一次外出采风时，他偶然捡到了一串钻石项链。虽然项链价值不...",
  "@type": "Movie",
  "aggregateRating": {
    "@type": "AggregateRating",
    "ratingCount": "0",
    "bestRating": "10",
    "worstRating": "2",
    "ratingValue": ""
  }
}
