
{
  "@context": "http://schema.org",
  "name": "浓厚血浆 Blood Runs Thick",
  "url": "/subject/26954705/",
  "image": "https://img2.doubanio.com/view/photo/s_ratio_poster/public/p2505680011.jpg",
  "director": 
  [
  ]
,
  "author": 
  [
  ]
,
  "actor": 
  [
    {
      "@type": "Person",
      "url": "/celebrity/1036371/",
      "name": "汤姆·塞兹摩尔 Tom Sizemore"
    }
    ,
    {
      "@type": "Person",
      "url": "/celebrity/1005095/",
      "name": "马修·阿什福德 Matthew Ashford"
    }
    ,
    {
      "@type": "Person",
      "url": "/celebrity/1114769/",
      "name": "Judi Evans Judi Evans"
    }
    ,
    {
      "@type": "Person",
      "url": "/celebrity/1383573/",
      "name": "扎卡里·亚力山大·赖斯 Zachary Alexander Rice"
    }
    ,
    {
      "@type": "Person",
      "url": "/celebrity/1229098/",
      "name": "斯利姆·克什里 Slim Khezri"
    }
  ]
,
  "datePublished": "2018-10-30",
  "genre": ["\u6050\u6016"],
  "duration": "PT1H30M",
  "description": "A beautiful young woman struggles with frightening hallucinations and a crumbling mental state after...",
  "@type": "Movie",
  "aggregateRating": {
    "@type": "AggregateRating",
    "ratingCount": "0",
    "bestRating": "10",
    "worstRating": "2",
    "ratingValue": ""
  }
}
