
{
  "@context": "http://schema.org",
  "name": "梦境心理女师",
  "url": "/subject/26986775/",
  "image": "https://img1.doubanio.com/view/photo/s_ratio_poster/public/p2437253878.jpg",
  "director": 
  [
  ]
,
  "author": 
  [
  ]
,
  "actor": 
  [
    {
      "@type": "Person",
      "url": "/celebrity/1326916/",
      "name": "张倩如 Qianru Zhang"
    }
    ,
    {
      "@type": "Person",
      "url": "/celebrity/1354439/",
      "name": "李钊 Zhao Li"
    }
  ]
,
  "datePublished": "",
  "genre": ["\u5267\u60c5", "\u60ac\u7591", "\u60ca\u609a"],
  "duration": "PT1H7M",
  "description": "面容清秀美丽的心理女师白丽，猖狂的复仇中，杀死了身边所有的亲人，因为手段的诡异，一次次逃过警方的调查，但她仍不罢休，亲生弟弟，算卦先生，以及世间虐待孩子的变态家长都在她猎杀的范围之内……警察队伍中的心...",
  "@type": "Movie",
  "aggregateRating": {
    "@type": "AggregateRating",
    "ratingCount": "0",
    "bestRating": "10",
    "worstRating": "2",
    "ratingValue": ""
  }
}
