
{
  "@context": "http://schema.org",
  "name": "盐马帮",
  "url": "/subject/27005332/",
  "image": "https://img9.doubanio.com/view/photo/s_ratio_poster/public/p2458662314.jpg",
  "director": 
  [
  ]
,
  "author": 
  [
  ]
,
  "actor": 
  [
  ]
,
  "datePublished": "2017-03-23",
  "genre": ["\u5267\u60c5", "\u52a8\u4f5c"],
  "duration": "PT1H28M",
  "description": "一九三六年，四川自流井盐埸。天义堂新收了两个为了跑马帮而加入袍哥组织的青年人。并被操武打的舵爷李九峰收为徒弟，赐名云龙和云虎。云龙一伙运盐巴的马队从自流井出发去云...",
  "@type": "Movie",
  "aggregateRating": {
    "@type": "AggregateRating",
    "ratingCount": "0",
    "bestRating": "10",
    "worstRating": "2",
    "ratingValue": ""
  }
}
