
{
  "@context": "http://schema.org",
  "name": "水手服忍者 セーラー服忍者",
  "url": "/subject/27089329/",
  "image": "https://img2.doubanio.com/view/photo/s_ratio_poster/public/p2494176391.jpg",
  "director": 
  [
  ]
,
  "author": 
  [
  ]
,
  "actor": 
  [
    {
      "@type": "Person",
      "url": "/celebrity/1353035/",
      "name": "鹤卷星奈 Seina Tsurumaki"
    }
  ]
,
  "datePublished": "2017-10-06",
  "genre": ["\u52a8\u4f5c"],
  "duration": "PT0H56M",
  "description": "時は安土桃山時代。忍びの郷を抜けた篠(17)は、追手から逃走する際に2015年にタイムスリップしてしまう。
たった一人で見知らぬ現代を彷徨う篠を救ったのは、篠そっくりの顔をした篠の子孫の服部優花(17...",
  "@type": "Movie",
  "aggregateRating": {
    "@type": "AggregateRating",
    "ratingCount": "0",
    "bestRating": "10",
    "worstRating": "2",
    "ratingValue": ""
  }
}
