
{
  "@context": "http://schema.org",
  "name": "天籁梦想",
  "url": "/subject/27170581/",
  "image": "https://img2.doubanio.com/view/photo/s_ratio_poster/public/p2504591731.jpg",
  "director": 
  [
    {
      "@type": "Person",
      "url": "/celebrity/1342506/",
      "name": "张唯 Wei Zhang"
    }
  ]
,
  "author": 
  [
    {
      "@type": "Person",
      "url": "/celebrity/1386715/",
      "name": "Gregory Marquette Gregory Marquette"
    }
    ,
    {
      "@type": "Person",
      "url": "/celebrity/1343094/",
      "name": "陈阳 Yang Chen"
    }
    ,
    {
      "@type": "Person",
      "url": "/celebrity/1386716/",
      "name": "陈睿睿 Ruirui Chen"
    }
    ,
    {
      "@type": "Person",
      "url": "/celebrity/1386717/",
      "name": "初征 Zheng Chu"
    }
  ]
,
  "actor": 
  [
    {
      "@type": "Person",
      "url": "/celebrity/1386718/",
      "name": "落松土登 "
    }
    ,
    {
      "@type": "Person",
      "url": "/celebrity/1386719/",
      "name": "益西旦增 "
    }
    ,
    {
      "@type": "Person",
      "url": "/celebrity/1386720/",
      "name": "嘎玛松姆 "
    }
    ,
    {
      "@type": "Person",
      "url": "/celebrity/1386721/",
      "name": "班玛久买 "
    }
    ,
    {
      "@type": "Person",
      "url": "/celebrity/1386722/",
      "name": "索朗旺堆 Sonam Wangmo"
    }
    ,
    {
      "@type": "Person",
      "url": "/celebrity/1386723/",
      "name": "阿旺卓玛 "
    }
  ]
,
  "datePublished": "2017-09-26",
  "genre": ["\u5267\u60c5", "\u5bb6\u5ead"],
  "duration": "PT1H25M",
  "description": "四个藏族盲童，从珠穆朗玛峰脚下的小村出发。为了一个上电视表演的梦想进行的冒险历程。他们是盲童，却用心去看整个世界。不屈从命运，不畏惧艰险，于黑暗中勇敢前行。他们来自于世界第三极，那里有丰富多彩的民俗文...",
  "@type": "Movie",
  "aggregateRating": {
    "@type": "AggregateRating",
    "ratingCount": "0",
    "bestRating": "10",
    "worstRating": "2",
    "ratingValue": ""
  }
}
