
{
  "@context": "http://schema.org",
  "name": "夜不语之终极驱魔",
  "url": "/subject/30121978/",
  "image": "https://img1.doubanio.com/view/photo/s_ratio_poster/public/p2512050389.jpg",
  "director": 
  [
    {
      "@type": "Person",
      "url": "/celebrity/1320110/",
      "name": "余庆 Qing Yu"
    }
  ]
,
  "author": 
  [
    {
      "@type": "Person",
      "url": "/celebrity/1388029/",
      "name": "娄恰 "
    }
  ]
,
  "actor": 
  [
    {
      "@type": "Person",
      "url": "/celebrity/1378944/",
      "name": "徐瑾 Jin Xu"
    }
    ,
    {
      "@type": "Person",
      "url": "/celebrity/1428787/",
      "name": "苏柏 subo"
    }
  ]
,
  "datePublished": "2018-01-30",
  "genre": ["\u79d1\u5e7b", "\u60ac\u7591"],
  "duration": "PT1H5M",
  "description": "东宁天降陨石雨，随陨石而来的神秘生物钻入了小女孩苏芒的大脑，身为植物人的后者忽然“醒来”，其主治医生也意外死亡。苏芒的姑姑苏青是脑科医生，面对科学不能解释的一切，她找到自己的留学校友、在大学任教的夜不...",
  "@type": "Movie",
  "aggregateRating": {
    "@type": "AggregateRating",
    "ratingCount": "0",
    "bestRating": "10",
    "worstRating": "2",
    "ratingValue": ""
  }
}
