
{
  "@context": "http://schema.org",
  "name": "少年的你",
  "url": "/subject/30166972/",
  "image": "https://img2.doubanio.com/view/photo/s_ratio_poster/public/p2572166063.jpg",
  "director": 
  [
    {
      "@type": "Person",
      "url": "/celebrity/1274534/",
      "name": "曾国祥 Derek Tsang"
    }
  ]
,
  "author": 
  [
    {
      "@type": "Person",
      "url": "/celebrity/1359881/",
      "name": "林咏琛 Lam Wing Sum"
    }
    ,
    {
      "@type": "Person",
      "url": "/celebrity/1359882/",
      "name": "李媛 Yuan Li"
    }
    ,
    {
      "@type": "Person",
      "url": "/celebrity/1330070/",
      "name": "许伊萌 Yimeng Xu"
    }
    ,
    {
      "@type": "Person",
      "url": "/celebrity/1410272/",
      "name": "玖月晞 Jiu Yue Xi"
    }
    ,
    {
      "@type": "Person",
      "url": "/celebrity/1428135/",
      "name": "陈楠 "
    }
  ]
,
  "actor": 
  [
    {
      "@type": "Person",
      "url": "/celebrity/1274224/",
      "name": "周冬雨 Dongyu Zhou"
    }
    ,
    {
      "@type": "Person",
      "url": "/celebrity/1340022/",
      "name": "易烊千玺 Jackson Yee"
    }
    ,
    {
      "@type": "Person",
      "url": "/celebrity/1340310/",
      "name": "尹昉 Fang Yin"
    }
    ,
    {
      "@type": "Person",
      "url": "/celebrity/1412762/",
      "name": "周也 Ye Zhou"
    }
    ,
    {
      "@type": "Person",
      "url": "/celebrity/1310696/",
      "name": "吴越 Yue Wu"
    }
    ,
    {
      "@type": "Person",
      "url": "/celebrity/1275273/",
      "name": "黄觉 Jue Huang"
    }
    ,
    {
      "@type": "Person",
      "url": "/celebrity/1416912/",
      "name": "张艺凡 Yifan Zhang"
    }
    ,
    {
      "@type": "Person",
      "url": "/celebrity/1404000/",
      "name": "张耀 Yao Zhang"
    }
    ,
    {
      "@type": "Person",
      "url": "/celebrity/1316839/",
      "name": "张歆怡 Xinyi Zhang"
    }
    ,
    {
      "@type": "Person",
      "url": "/celebrity/1416890/",
      "name": "赵润南 Runnan Zhao"
    }
    ,
    {
      "@type": "Person",
      "url": "/celebrity/1403652/",
      "name": "郜玄铭 Xuanming Gao"
    }
    ,
    {
      "@type": "Person",
      "url": "/celebrity/1388037/",
      "name": "谢欣桐 Xintong Xie"
    }
    ,
    {
      "@type": "Person",
      "url": "/celebrity/1423406/",
      "name": "刘然 Ran Liu"
    }
    ,
    {
      "@type": "Person",
      "url": "/celebrity/1414577/",
      "name": "何廖侣匀 Lüyun Heliao"
    }
    ,
    {
      "@type": "Person",
      "url": "/celebrity/1425410/",
      "name": "胖虎 Pan Hu"
    }
    ,
    {
      "@type": "Person",
      "url": "/celebrity/1425579/",
      "name": "王英明 Yingming Wang"
    }
    ,
    {
      "@type": "Person",
      "url": "/celebrity/1425576/",
      "name": "李伟龙 Weilong Li"
    }
    ,
    {
      "@type": "Person",
      "url": "/celebrity/1440378/",
      "name": "郭钟宇 Zhongyu Guo"
    }
    ,
    {
      "@type": "Person",
      "url": "/celebrity/1440463/",
      "name": "孙岩 Yan Sun"
    }
    ,
    {
      "@type": "Person",
      "url": "/celebrity/1440372/",
      "name": "陈清銮 Meehz Chen"
    }
    ,
    {
      "@type": "Person",
      "url": "/celebrity/1440453/",
      "name": "黎真承 Zhencheng Li"
    }
  ]
,
  "datePublished": "2019-10-25",
  "genre": ["\u5267\u60c5", "\u7231\u60c5", "\u72af\u7f6a"],
  "duration": "PT2H15M",
  "description": "陈念（周冬雨 饰）是一名即将参加高考的高三学生，同校女生胡晓蝶（张艺凡 饰）的跳楼自杀让她的生活陷入了困顿之中。胡晓蝶死后，陈念遭到了以魏莱（周也 饰）为首的三人组的霸凌，魏莱虽然表面上看来是乖巧的优...",
  "@type": "Movie",
  "aggregateRating": {
    "@type": "AggregateRating",
    "ratingCount": "1431347",
    "bestRating": "10",
    "worstRating": "2",
    "ratingValue": "8.2"
  }
}
