
{
  "@context": "http://schema.org",
  "name": "心霊闇動画24",
  "url": "/subject/30190609/",
  "image": "https://img1.doubanio.com/view/photo/s_ratio_poster/public/p2518735409.jpg",
  "director": 
  [
  ]
,
  "author": 
  [
  ]
,
  "actor": 
  [
  ]
,
  "datePublished": "",
  "genre": ["\u6050\u6016"],
  "duration": "",
  "description": "エレベーター
デパートの従業員専用エレベーターを記録した監視カメラの映像。撮影の数日後に自殺したという従業員がうつる箇所に不可解な存在が…。
連れてゆく
心霊スポット巡りが趣味だという男性２人が夜のト...",
  "@type": "Movie",
  "aggregateRating": {
    "@type": "AggregateRating",
    "ratingCount": "0",
    "bestRating": "10",
    "worstRating": "2",
    "ratingValue": ""
  }
}
