
{
  "@context": "http://schema.org",
  "name": "泄露天机·囚妻",
  "url": "/subject/30200086/",
  "image": "https://img1.doubanio.com/view/photo/s_ratio_poster/public/p2882610038.jpg",
  "director": 
  [
  ]
,
  "author": 
  [
  ]
,
  "actor": 
  [
    {
      "@type": "Person",
      "url": "/celebrity/1337236/",
      "name": "廖梦妍 Mengyan Liao"
    }
  ]
,
  "datePublished": "2018-04-16",
  "genre": ["\u7231\u60c5", "\u60ac\u7591", "\u72af\u7f6a"],
  "duration": "PT0H43M",
  "description": "梁启霞受不了丈夫程方生的家庭暴力，提出离婚诉讼，程方生百般阻拦，启霞还是收拾东西离开。启霞误上了张荣亨的车，结果引起程方生更深的误会，怀疑妻子与张荣亨有关系，于是便前往张家调查，然而他发现了一个秘密，...",
  "@type": "Movie",
  "aggregateRating": {
    "@type": "AggregateRating",
    "ratingCount": "0",
    "bestRating": "10",
    "worstRating": "2",
    "ratingValue": ""
  }
}
