
{
  "@context": "http://schema.org",
  "name": "黑南瓜头 Black Pumpkin",
  "url": "/subject/30257436/",
  "image": "https://img9.doubanio.com/view/photo/s_ratio_poster/public/p2624590525.jpg",
  "director": 
  [
  ]
,
  "author": 
  [
  ]
,
  "actor": 
  [
    {
      "@type": "Person",
      "url": "/celebrity/1234671/",
      "name": "乔·奥斯蒙德 Jo Osmond"
    }
    ,
    {
      "@type": "Person",
      "url": "/celebrity/1360270/",
      "name": "Connor Weil Connor Weil"
    }
    ,
    {
      "@type": "Person",
      "url": "/celebrity/1387912/",
      "name": "卡米拉·艾尔内斯 Kamilla Alnes"
    }
    ,
    {
      "@type": "Person",
      "url": "/celebrity/1258439/",
      "name": "布兰妮·柏尔特 Brittany Belt"
    }
    ,
    {
      "@type": "Person",
      "url": "/celebrity/1074195/",
      "name": "柯特·克伦德尼 Curt Clendenin"
    }
    ,
    {
      "@type": "Person",
      "url": "/celebrity/1454224/",
      "name": "Ellie Patrikios Ellie Patrikios"
    }
    ,
    {
      "@type": "Person",
      "url": "/celebrity/1465124/",
      "name": "杰玛·布鲁克·艾伦 Gemma Brooke Allen"
    }
  ]
,
  "datePublished": "",
  "genre": ["\u6050\u6016"],
  "duration": "",
  "description": "On October 31, 2018, two preteens in a small town accidentally awaken an evil that has lain dormant ...",
  "@type": "Movie",
  "aggregateRating": {
    "@type": "AggregateRating",
    "ratingCount": "0",
    "bestRating": "10",
    "worstRating": "2",
    "ratingValue": ""
  }
}
