
{
  "@context": "http://schema.org",
  "name": "Hanuman vs. Mahiravana",
  "url": "/subject/30415026/",
  "image": "https://img2.doubanio.com/view/photo/s_ratio_poster/public/p2543796802.jpg",
  "director": 
  [
  ]
,
  "author": 
  [
  ]
,
  "actor": 
  [
  ]
,
  "datePublished": "2018-07-06",
  "genre": ["\u52a8\u753b"],
  "duration": "PT1H31M",
  "description": "The quest to rescue princess Sita is coming to an end as Rama and his army of monkeys make their fin...",
  "@type": "Movie",
  "aggregateRating": {
    "@type": "AggregateRating",
    "ratingCount": "0",
    "bestRating": "10",
    "worstRating": "2",
    "ratingValue": ""
  }
}
