
{
  "@context": "http://schema.org",
  "name": "菲凡记忆",
  "url": "/subject/30450410/",
  "image": "https://img1.doubanio.com/view/photo/s_ratio_poster/public/p2551162358.jpg",
  "director": 
  [
    {
      "@type": "Person",
      "url": "/celebrity/1365003/",
      "name": "田重 Zhong Tian"
    }
  ]
,
  "author": 
  [
    {
      "@type": "Person",
      "url": "/celebrity/1411258/",
      "name": "曾维正 Weizheng Zeng"
    }
  ]
,
  "actor": 
  [
    {
      "@type": "Person",
      "url": "/celebrity/1409112/",
      "name": "张奕 Yi Zhang"
    }
    ,
    {
      "@type": "Person",
      "url": "/celebrity/1044611/",
      "name": "保剑锋 Jianfeng Bao"
    }
    ,
    {
      "@type": "Person",
      "url": "/celebrity/1392642/",
      "name": "李嘉铭 Jiaming Li"
    }
    ,
    {
      "@type": "Person",
      "url": "/celebrity/1315055/",
      "name": "梁又琳 You-lin Liang"
    }
    ,
    {
      "@type": "Person",
      "url": "/celebrity/1437447/",
      "name": "赵辰熙 Chenxi Zhao"
    }
  ]
,
  "datePublished": "2019-04-12",
  "genre": ["\u559c\u5267", "\u7231\u60c5", "\u5947\u5e7b"],
  "duration": "PT1H37M",
  "description": "拥有超凡记忆并能心灵感应他人思维的田菲凡，受到企业家刘沉毅的暗中瞩目，巧妙将其安排进入美妆公司担任妻子王雅琴的特助。田菲凡凭借超能力从业界菜鸟，蜕变为时尚女神。成长过程中，田菲凡因超凡记忆和其心灵感应...",
  "@type": "Movie",
  "aggregateRating": {
    "@type": "AggregateRating",
    "ratingCount": "0",
    "bestRating": "10",
    "worstRating": "2",
    "ratingValue": ""
  }
}
