
{
  "@context": "http://schema.org",
  "name": "醒来之爱的呼唤",
  "url": "/subject/30460368/",
  "image": "https://img1.doubanio.com/view/photo/s_ratio_poster/public/p2549170039.jpg",
  "director": 
  [
    {
      "@type": "Person",
      "url": "/celebrity/1391938/",
      "name": "王陆涛 Lutao Wang"
    }
  ]
,
  "author": 
  [
    {
      "@type": "Person",
      "url": "/celebrity/1391939/",
      "name": "李爱玲 Ailing Li"
    }
  ]
,
  "actor": 
  [
    {
      "@type": "Person",
      "url": "/celebrity/1321589/",
      "name": "李梦男 Mengnan Li"
    }
    ,
    {
      "@type": "Person",
      "url": "/celebrity/1334751/",
      "name": "张琛 Chen Zhang"
    }
    ,
    {
      "@type": "Person",
      "url": "/celebrity/1318445/",
      "name": "傅冲 Chong Fu"
    }
    ,
    {
      "@type": "Person",
      "url": "/celebrity/1322771/",
      "name": "王超 Chao Wang"
    }
    ,
    {
      "@type": "Person",
      "url": "/celebrity/1316513/",
      "name": "马东延 Dongyan Ma"
    }
    ,
    {
      "@type": "Person",
      "url": "/celebrity/1350012/",
      "name": "王婷 Ting Wang"
    }
    ,
    {
      "@type": "Person",
      "url": "/celebrity/1411432/",
      "name": "张硕 Shuo Zhang"
    }
    ,
    {
      "@type": "Person",
      "url": "/celebrity/1412325/",
      "name": "王春来 "
    }
  ]
,
  "datePublished": "2019-03-08",
  "genre": ["\u5267\u60c5"],
  "duration": "PT1H46M",
  "description": "在监狱服刑十八年的志刚终于刑满释放，当年的桀骜不驯和自负轻狂，经过狱中漫长传统文化的洗礼和渗透，神情中已不见锋芒。重获新生后的一切都是未知。志刚此刻只想知道，阔别已久的社会和家庭，还能不能接纳改过一新...",
  "@type": "Movie",
  "aggregateRating": {
    "@type": "AggregateRating",
    "ratingCount": "0",
    "bestRating": "10",
    "worstRating": "2",
    "ratingValue": ""
  }
}
