
{
  "@context": "http://schema.org",
  "name": "麻烦专家",
  "url": "/subject/33372004/",
  "image": "https://img1.doubanio.com/view/photo/s_ratio_poster/public/p2551434769.jpg",
  "director": 
  [
  ]
,
  "author": 
  [
  ]
,
  "actor": 
  [
    {
      "@type": "Person",
      "url": "/celebrity/1429218/",
      "name": "韩金明 "
    }
  ]
,
  "datePublished": "2019-03-21",
  "genre": ["\u7231\u60c5", "\u8fd0\u52a8"],
  "duration": "PT1H33M",
  "description": "“麻烦专家”吴忧专门解决各种麻烦。一天，他接到一个高额报酬的任务：接近女大学生刘一晨获得信任并劝她放弃财产协议。 吴忧使尽浑身解数获取刘一晨签名都没有成功，反而越来越觉得刘一晨不像雇主嘴里贪图财产的第...",
  "@type": "Movie",
  "aggregateRating": {
    "@type": "AggregateRating",
    "ratingCount": "0",
    "bestRating": "10",
    "worstRating": "2",
    "ratingValue": ""
  }
}
