
{
  "@context": "http://schema.org",
  "name": "弗朗西斯科·德卡洛：世间百态 Francesco de Carlo: Cose di Questo Mondo",
  "url": "/subject/33413686/",
  "image": "https://img1.doubanio.com/view/photo/s_ratio_poster/public/p2553822368.jpg",
  "director": 
  [
  ]
,
  "author": 
  [
  ]
,
  "actor": 
  [
  ]
,
  "datePublished": "2019-04-12",
  "genre": ["\u559c\u5267", "\u8131\u53e3\u79c0"],
  "duration": "PT1H1M",
  "description": "在米兰的舞台上，弗朗西斯科·德卡洛畅谈他的坏习惯、宗教、政治以及他从周游世界中学到的东西",
  "@type": "Movie",
  "aggregateRating": {
    "@type": "AggregateRating",
    "ratingCount": "0",
    "bestRating": "10",
    "worstRating": "2",
    "ratingValue": ""
  }
}
