
{
  "@context": "http://schema.org",
  "name": "卡尔·马克思：最后的旅程 Karl Max: The Last Journey",
  "url": "/subject/26973618/",
  "image": "https://img1.doubanio.com/f/movie/30c6263b6db26d055cbbe73fe653e29014142ea3/pics/movie/movie_default_large.png",
  "director": 
  [
    {
      "@type": "Person",
      "url": "/celebrity/1274667/",
      "name": "王全安 Quan&#39;an Wang"
    }
    ,
    {
      "@type": "Person",
      "url": "/celebrity/1050273/",
      "name": "马里奥·阿多夫 Mario Adorf"
    }
  ]
,
  "author": 
  [
  ]
,
  "actor": 
  [
    {
      "@type": "Person",
      "url": "/celebrity/1050273/",
      "name": "马里奥·阿多夫 Mario Adorf"
    }
  ]
,
  "datePublished": "",
  "genre": ["\u4f20\u8bb0"],
  "duration": "",
  "description": "王全安将同马里奥·阿多夫合作新片[卡尔·马克思：最后的旅程](Karl Max:The Last Journey，暂译)。电影根据发生在1870年的真实事件改编，马克思当时被朋友恩格斯敦促，以健康为由...",
  "@type": "Movie",
  "aggregateRating": {
    "@type": "AggregateRating",
    "ratingCount": "0",
    "bestRating": "10",
    "worstRating": "2",
    "ratingValue": ""
  }
}
