
{
  "@context": "http://schema.org",
  "name": "天·火",
  "url": "/subject/30357885/",
  "image": "https://img2.doubanio.com/view/photo/s_ratio_poster/public/p2576728533.jpg",
  "director": 
  [
    {
      "@type": "Person",
      "url": "/celebrity/1300732/",
      "name": "西蒙·韦斯特 Simon West"
    }
  ]
,
  "author": 
  [
    {
      "@type": "Person",
      "url": "/celebrity/1402963/",
      "name": "卜维 "
    }
    ,
    {
      "@type": "Person",
      "url": "/celebrity/1308285/",
      "name": "西德尼·金 Sidney King"
    }
  ]
,
  "actor": 
  [
    {
      "@type": "Person",
      "url": "/celebrity/1054562/",
      "name": "王学圻 Xueqi Wang"
    }
    ,
    {
      "@type": "Person",
      "url": "/celebrity/1313866/",
      "name": "昆凌 Hannah Quinlivan"
    }
    ,
    {
      "@type": "Person",
      "url": "/celebrity/1274225/",
      "name": "窦骁 Shawn Dou"
    }
    ,
    {
      "@type": "Person",
      "url": "/celebrity/1017916/",
      "name": "詹森·艾萨克 Jason Isaacs"
    }
    ,
    {
      "@type": "Person",
      "url": "/celebrity/1323837/",
      "name": "柏安 An Bai"
    }
    ,
    {
      "@type": "Person",
      "url": "/celebrity/1382682/",
      "name": "纪凌尘 Lingchen Ji"
    }
    ,
    {
      "@type": "Person",
      "url": "/celebrity/1313009/",
      "name": "石凉 Liang Shi"
    }
    ,
    {
      "@type": "Person",
      "url": "/celebrity/1428108/",
      "name": "爱丽丝·里特韦尔 Alice Rietveld"
    }
    ,
    {
      "@type": "Person",
      "url": "/celebrity/1342810/",
      "name": "李一情 Yiqing Li"
    }
    ,
    {
      "@type": "Person",
      "url": "/celebrity/1402964/",
      "name": "比兰德·罗杰斯 Beeland Rogers"
    }
    ,
    {
      "@type": "Person",
      "url": "/celebrity/1336345/",
      "name": "马昕墨 Leslie Ma"
    }
    ,
    {
      "@type": "Person",
      "url": "/celebrity/1326724/",
      "name": "侯桐江 Tongjiang Hou"
    }
    ,
    {
      "@type": "Person",
      "url": "/celebrity/1412435/",
      "name": "陈依琪 Yiqi Chen"
    }
    ,
    {
      "@type": "Person",
      "url": "/celebrity/1374064/",
      "name": "郎永淳 Yongchun Lang"
    }
    ,
    {
      "@type": "Person",
      "url": "/celebrity/1402965/",
      "name": "吴汉钧 Hanjun Wu"
    }
  ]
,
  "datePublished": "2019-12-12",
  "genre": ["\u52a8\u4f5c", "\u5192\u9669", "\u707e\u96be"],
  "duration": "PT1H37M",
  "description": "天火岛美得如同世外桃源，几乎让人忘记它位于“Ring of Fire”——全球知名的环太平洋火山带。年轻的地质学家李晓梦为了研发首个火山监测系统“朱雀”，带着团队来到了这里。李晓梦的父亲、隐退多年的火...",
  "@type": "Movie",
  "aggregateRating": {
    "@type": "AggregateRating",
    "ratingCount": "19122",
    "bestRating": "10",
    "worstRating": "2",
    "ratingValue": "4.2"
  }
}
