
{
  "@context": "http://schema.org",
  "name": "一墙之隔",
  "url": "/subject/4272554/",
  "image": "https://img9.doubanio.com/view/photo/s_ratio_poster/public/p2553582956.jpg",
  "director": 
  [
    {
      "@type": "Person",
      "url": "/celebrity/1328785/",
      "name": "陈双印 Shuangyin Chen"
    }
  ]
,
  "author": 
  [
    {
      "@type": "Person",
      "url": "/celebrity/1328785/",
      "name": "陈双印 Shuangyin Chen"
    }
  ]
,
  "actor": 
  [
    {
      "@type": "Person",
      "url": "/celebrity/1041734/",
      "name": "朱茵 Athena Chu"
    }
    ,
    {
      "@type": "Person",
      "url": "/celebrity/1274479/",
      "name": "唐嫣 Yan Tang"
    }
    ,
    {
      "@type": "Person",
      "url": "/celebrity/1023141/",
      "name": "孟广美 Jessey Meng"
    }
    ,
    {
      "@type": "Person",
      "url": "/celebrity/1315091/",
      "name": "杨青 Qing Yang"
    }
    ,
    {
      "@type": "Person",
      "url": "/celebrity/1274429/",
      "name": "斯琴高娃 Gaowa Siqin"
    }
    ,
    {
      "@type": "Person",
      "url": "/celebrity/1317039/",
      "name": "董立范 Lifan Dong"
    }
    ,
    {
      "@type": "Person",
      "url": "/celebrity/1275275/",
      "name": "王姬 Ji Wang"
    }
    ,
    {
      "@type": "Person",
      "url": "/celebrity/1336093/",
      "name": "夏炎 Yan Xia"
    }
    ,
    {
      "@type": "Person",
      "url": "/celebrity/1275294/",
      "name": "金铭 Ming Jin"
    }
    ,
    {
      "@type": "Person",
      "url": "/celebrity/1316067/",
      "name": "袁姗姗 Shanshan Yuan"
    }
    ,
    {
      "@type": "Person",
      "url": "/celebrity/1033481/",
      "name": "叶童 Cecilia Yip"
    }
  ]
,
  "datePublished": "",
  "genre": ["\u5267\u60c5", "\u60ac\u7591", "\u72af\u7f6a"],
  "duration": "",
  "description": "《让爱回家》的故事发生在女子监狱里一个最差劲的监室，几个女孩自暴自弃，面对着绝望的生活几欲崩溃。但在年轻狱警帮助下，这群女孩终于勇敢地站了起来去面对未来的生活。",
  "@type": "Movie",
  "aggregateRating": {
    "@type": "AggregateRating",
    "ratingCount": "0",
    "bestRating": "10",
    "worstRating": "2",
    "ratingValue": ""
  }
}
